fem4room/Boundary.py
fem4room/Simulation.py
fem4room/Solver.py
fem4room/TimeEngine.py
fem4room/Tools.py
fem4room/__init__.py
fem4room/FEM_2D/Engine.py
fem4room/FEM_2D/Mesh.py
fem4room/FEM_2D/Utils.py
fem4room/FEM_2D/__init__.py
fem4room/FEM_3D/Engine.py
fem4room/FEM_3D/Mesh.py
fem4room/FEM_3D/__init__.py
fem4room-0.0.2.dev5.dist-info/LICENSE
fem4room-0.0.2.dev5.dist-info/METADATA
fem4room-0.0.2.dev5.dist-info/WHEEL
fem4room-0.0.2.dev5.dist-info/top_level.txt
fem4room-0.0.2.dev5.dist-info/RECORD
