Metadata-Version: 2.1
Name: fem4room
Version: 0.0.2.dev5
Summary: Room Acoustics Simulation. Retrieve room impulse response using finite elements method.
Home-page: https://github.com/aldalmora/fem4room
Author: André Luiz Dalmora
Author-email: andre.dalmora@gmail.com
License: UNKNOWN
Keywords: room acoustics finite elements method impulse response
Platform: UNKNOWN
Classifier: Programming Language :: Python :: 3
Classifier: License :: OSI Approved :: GNU General Public License v3 (GPLv3)
Classifier: Intended Audience :: Science/Research
Classifier: Topic :: Scientific/Engineering
Classifier: Development Status :: 4 - Beta
Requires-Python: >=3.6
Requires-Dist: scipy
Requires-Dist: gmsh-sdk (>=4.6)
Requires-Dist: matplotlib (>=3)
Requires-Dist: ezdxf (~=0.13.1)
